{
	"configurations" : 
	[
		{
			"directories" : 
			[
				{
					"build" : ".",
					"jsonFile" : "directory-.-Debug-f5ebdc15457944623624.json",
					"minimumCMakeVersion" : 
					{
						"string" : "3.24"
					},
					"projectIndex" : 0,
					"source" : ".",
					"targetIndexes" : 
					[
						0
					]
				}
			],
			"name" : "Debug",
			"projects" : 
			[
				{
					"directoryIndexes" : 
					[
						0
					],
					"name" : "2205",
					"targetIndexes" : 
					[
						0
					]
				}
			],
			"targets" : 
			[
				{
					"directoryIndex" : 0,
					"id" : "2205::@6890427a1f51a3e7e1df",
					"jsonFile" : "target-2205-Debug-d5c850cb54182985b13c.json",
					"name" : "2205",
					"projectIndex" : 0
				}
			]
		}
	],
	"kind" : "codemodel",
	"paths" : 
	{
		"build" : "/Users/poyujuan/Program/OJ-practice/CSES/Intro/2205/cmake-build-debug",
		"source" : "/Users/poyujuan/Program/OJ-practice/CSES/Intro/2205"
	},
	"version" : 
	{
		"major" : 2,
		"minor" : 4
	}
}
